LICENSE
README.md
setup.cfg
setup.py
mds3/__init__.py
mds3/__main__.py
mds3/info.py
mds3/output.py
mds3/s3.py
mds3/version.py
mds3.egg-info/PKG-INFO
mds3.egg-info/SOURCES.txt
mds3.egg-info/dependency_links.txt
mds3.egg-info/entry_points.txt
mds3.egg-info/requires.txt
mds3.egg-info/top_level.txt
mds3.egg-info/zip-safe