Metadata-Version: 2.1
Name: mds3
Version: 1.0.1
Summary: MySQL Dump to S3
Home-page: https://ouroboroscoding.com/mds3
Author: Chris Nasr - OuroborosCoding
Author-email: chris@ouroboroscoding.com
License: MIT
Project-URL: Source, https://github.com/ouroboroscoding/mds3
Project-URL: Tracker, https://github.com/ouroboroscoding/mds3/issues
Keywords: mysql,mysqldump,backup,s3,aws
Platform: UNKNOWN
Requires-Python: >=3.10
License-File: LICENSE
